pygitgrab/__init__.py
pygitgrab/__main__.py
pygitgrab/configreader.py
pygitgrab/extract.py
pygitgrab/gitgrab.py
pygitgrab/pygitgrab.py
pygitgrab/readuserinfo.py
pygitgrab-0.0.20.dist-info/LICENSE
pygitgrab-0.0.20.dist-info/METADATA
pygitgrab-0.0.20.dist-info/WHEEL
pygitgrab-0.0.20.dist-info/entry_points.txt
pygitgrab-0.0.20.dist-info/top_level.txt
pygitgrab-0.0.20.dist-info/RECORD
