Metadata-Version: 2.1
Name: pygitgrab
Version: 0.0.20
Summary: grab only certain information from remote git repo and store them local
Home-page: https://github.com/kr-g/pygitgrab
Author: k.r. goger
Author-email: k.r.goger+pygitgrab@gmail.com
License: MIT
Keywords: python utility shell,git
Platform: UNKNOWN
Classifier: Development Status :: 3 - Alpha
Classifier: Operating System :: POSIX :: Linux
Classifier: Environment :: Console
Classifier: Intended Audience :: Developers
Classifier: Topic :: Utilities
Classifier: Programming Language :: Python :: 3
Classifier: License :: OSI Approved :: MIT License
Requires-Python: >=3.6
License-File: LICENSE
Requires-Dist: requests
